euler_gl-0.1.2.data/purelib/euler/__init__.py
euler_gl-0.1.2.data/purelib/euler/python/__init__.py
euler_gl-0.1.2.data/purelib/euler/python/libeuler_service.so
euler_gl-0.1.2.data/purelib/euler/python/service.py
euler_gl-0.1.2.data/purelib/euler/tools/__init__.py
euler_gl-0.1.2.data/purelib/euler/tools/__main__.py
euler_gl-0.1.2.data/purelib/euler/tools/json2dat.py
euler_gl-0.1.2.data/purelib/tf_euler/__init__.py
euler_gl-0.1.2.data/purelib/tf_euler/__main__.py
euler_gl-0.1.2.data/purelib/tf_euler/python/__init__.py
euler_gl-0.1.2.data/purelib/tf_euler/python/aggregators.py
euler_gl-0.1.2.data/purelib/tf_euler/python/base_layers.py
euler_gl-0.1.2.data/purelib/tf_euler/python/encoders.py
euler_gl-0.1.2.data/purelib/tf_euler/python/layers.py
euler_gl-0.1.2.data/purelib/tf_euler/python/metrics.py
euler_gl-0.1.2.data/purelib/tf_euler/python/optimizers.py
euler_gl-0.1.2.data/purelib/tf_euler/python/ppi_main.py
euler_gl-0.1.2.data/purelib/tf_euler/python/reddit_main.py
euler_gl-0.1.2.data/purelib/tf_euler/python/run_loop.py
euler_gl-0.1.2.data/purelib/tf_euler/python/sparse_aggregators.py
euler_gl-0.1.2.data/purelib/tf_euler/python/euler_ops/__init__.py
euler_gl-0.1.2.data/purelib/tf_euler/python/euler_ops/base.py
euler_gl-0.1.2.data/purelib/tf_euler/python/euler_ops/base_test.py
euler_gl-0.1.2.data/purelib/tf_euler/python/euler_ops/feature_ops.py
euler_gl-0.1.2.data/purelib/tf_euler/python/euler_ops/feature_ops_test.py
euler_gl-0.1.2.data/purelib/tf_euler/python/euler_ops/libclient.so
euler_gl-0.1.2.data/purelib/tf_euler/python/euler_ops/libtf_euler.so
euler_gl-0.1.2.data/purelib/tf_euler/python/euler_ops/neighbor_ops.py
euler_gl-0.1.2.data/purelib/tf_euler/python/euler_ops/neighbor_ops_test.py
euler_gl-0.1.2.data/purelib/tf_euler/python/euler_ops/sample_ops.py
euler_gl-0.1.2.data/purelib/tf_euler/python/euler_ops/sample_ops_test.py
euler_gl-0.1.2.data/purelib/tf_euler/python/euler_ops/type_ops.py
euler_gl-0.1.2.data/purelib/tf_euler/python/euler_ops/type_ops_test.py
euler_gl-0.1.2.dist-info/LICENSE
euler_gl-0.1.2.dist-info/METADATA
euler_gl-0.1.2.dist-info/WHEEL
euler_gl-0.1.2.dist-info/top_level.txt
euler_gl-0.1.2.dist-info/RECORD
