Metadata-Version: 2.1
Name: euler-gl
Version: 0.1.2
Summary: A toolset for network representation learning.
Home-page: https://github.com/alibaba/euler
Author: Alibaba Group Holding Limited
Author-email: euler-opensource@list.alibaba-inc.com
License: Apache License 2.0
Platform: UNKNOWN
Requires-Dist: tensorflow (==1.12.0)
